scholarvista/__init__.py
scholarvista/_utils.py
scholarvista/cli/__init__.py
scholarvista/cli/scholarvista.py
scholarvista/cli/utils/__init__.py
scholarvista/cli/utils/generate_figures_histogram.py
scholarvista/cli/utils/generate_keyword_clouds.py
scholarvista/cli/utils/generate_links_list.py
scholarvista/cli/utils/parse_pdfs.py
scholarvista/cli/utils/parse_tei_xmls.py
scholarvista/exceptions/__init__.py
scholarvista/exceptions/tag_not_found_in_tei_xml.py
scholarvista/keyword_cloud.py
scholarvista/pdf_parser.py
scholarvista/plotter.py
scholarvista/tei_xml_parser.py
scholarvista-0.1.3.dist-info/LICENSE
scholarvista-0.1.3.dist-info/METADATA
scholarvista-0.1.3.dist-info/WHEEL
scholarvista-0.1.3.dist-info/entry_points.txt
scholarvista-0.1.3.dist-info/RECORD
