Metadata-Version: 2.1
Name: scholarvista
Version: 0.1.3
Summary: ScholarVista is a tool that analyzes research papers and extracts and plots information from them. It utilizes Grobid, a library for extracting content from research papers, to extract all the relevant data. The extracted data is then plotted and displayed using Python.
License: Apache-2.0
Author: mciccale
Author-email: marcociccalebaztan@gmail.com
Requires-Python: >=3.12,<4.0
Classifier: License :: OSI Approved :: Apache Software License
Classifier: Programming Language :: Python :: 3
Classifier: Programming Language :: Python :: 3.12
Requires-Dist: click (>=8.1.7,<9.0.0)
Requires-Dist: grobid-client-python (>=0.0.8,<0.0.9)
Requires-Dist: matplotlib (>=3.8.2,<4.0.0)
Requires-Dist: wordcloud (>=1.9.3,<2.0.0)
